{
  "node": {
    "id": 1081,
    "name": "ConcatArray",
    "kind": 256,
    "kindString": "Interface",
    "flags": {
      "isExternal": true
    },
    "children": [
      {
        "id": 1082,
        "name": "length",
        "kind": 1024,
        "kindString": "Property",
        "flags": {
          "isExternal": true,
          "isReadonly": true
        },
        "sources": [
          {
            "fileName": "node_modules/typescript/lib/lib.es5.d.ts",
            "line": 1263,
            "character": 13
          }
        ],
        "type": {
          "type": "intrinsic",
          "name": "number"
        }
      },
      {
        "id": 1083,
        "name": "join",
        "kind": 2048,
        "kindString": "Method",
        "flags": {
          "isExternal": true
        },
        "signatures": [
          {
            "id": 1084,
            "name": "join",
            "kind": 4096,
            "kindString": "Call signature",
            "flags": {
              "isExternal": true
            },
            "parameters": [
              {
                "id": 1085,
                "name": "separator",
                "kind": 32768,
                "kindString": "Parameter",
                "flags": {
                  "isExternal": true,
                  "isOptional": true
                },
                "type": {
                  "type": "intrinsic",
                  "name": "string"
                }
              }
            ],
            "type": {
              "type": "intrinsic",
              "name": "string"
            }
          }
        ]
      },
      {
        "id": 1086,
        "name": "slice",
        "kind": 2048,
        "kindString": "Method",
        "flags": {
          "isExternal": true
        },
        "signatures": [
          {
            "id": 1087,
            "name": "slice",
            "kind": 4096,
            "kindString": "Call signature",
            "flags": {
              "isExternal": true
            },
            "parameters": [
              {
                "id": 1088,
                "name": "start",
                "kind": 32768,
                "kindString": "Parameter",
                "flags": {
                  "isExternal": true,
                  "isOptional": true
                },
                "type": {
                  "type": "intrinsic",
                  "name": "number"
                }
              },
              {
                "id": 1089,
                "name": "end",
                "kind": 32768,
                "kindString": "Parameter",
                "flags": {
                  "isExternal": true,
                  "isOptional": true
                },
                "type": {
                  "type": "intrinsic",
                  "name": "number"
                }
              }
            ],
            "type": {
              "type": "array",
              "elementType": {
                "type": "reference",
                "id": 1090,
                "qualifiedName": "ConcatArray.T",
                "package": "typescript",
                "name": "T"
              }
            }
          }
        ]
      }
    ],
    "groups": [
      {
        "title": "Properties",
        "kind": 1024,
        "children": [1082]
      },
      {
        "title": "Methods",
        "kind": 2048,
        "children": [1083, 1086]
      }
    ],
    "sources": [
      {
        "fileName": "node_modules/typescript/lib/lib.es5.d.ts",
        "line": 1262,
        "character": 10
      }
    ],
    "typeParameter": [
      {
        "id": 1090,
        "name": "T",
        "kind": 131072,
        "kindString": "Type parameter",
        "flags": {
          "isExternal": true
        }
      }
    ],
    "indexSignature": {
      "id": 1091,
      "name": "__index",
      "kind": 8192,
      "kindString": "Index signature",
      "flags": {
        "isExternal": true
      },
      "parameters": [
        {
          "id": 1092,
          "name": "n",
          "kind": 32768,
          "flags": {
            "isExternal": true
          },
          "type": {
            "type": "intrinsic",
            "name": "number"
          }
        }
      ],
      "type": {
        "type": "reference",
        "id": 1090,
        "qualifiedName": "ConcatArray.T",
        "package": "typescript",
        "name": "T"
      }
    }
  },
  "references": {},
  "meta": {
    "packageName": "typescript",
    "permaLink": "typescript/lib/ConcatArray",
    "menuGroup": "default"
  }
}
